AUTHORS.rst
CONTRIBUTING.rst
HISTORY.rst
LICENSE.txt
MANIFEST.in
README.rst
setup.cfg
setup.py
versioneer.py
docs/Makefile
docs/api.rst
docs/authors.rst
docs/conf.py
docs/contributing.rst
docs/history.rst
docs/index.rst
docs/installation.rst
docs/make.bat
docs/readme.rst
docs/usage.rst
npctypes/__init__.py
npctypes/_version.py
npctypes/shared.py
npctypes/types.py
npctypes.egg-info/PKG-INFO
npctypes.egg-info/SOURCES.txt
npctypes.egg-info/dependency_links.txt
npctypes.egg-info/not-zip-safe
npctypes.egg-info/requires.txt
npctypes.egg-info/top_level.txt
tests/__init__.py
tests/test_shared.py
tests/test_types.py